MANIFEST.in
README.rst
setup.py
aliyun_python_sdk_airec_test.egg-info/PKG-INFO
aliyun_python_sdk_airec_test.egg-info/SOURCES.txt
aliyun_python_sdk_airec_test.egg-info/dependency_links.txt
aliyun_python_sdk_airec_test.egg-info/requires.txt
aliyun_python_sdk_airec_test.egg-info/top_level.txt
aliyunsdkairec/__init__.py
aliyunsdkairec/request/__init__.py
aliyunsdkairec/request/v20181012/AttachDatasetRequest.py
aliyunsdkairec/request/v20181012/CreateDiversifyRequest.py
aliyunsdkairec/request/v20181012/CreateInstanceRequest.py
aliyunsdkairec/request/v20181012/CreateMixRequest.py
aliyunsdkairec/request/v20181012/DeleteDataSetRequest.py
aliyunsdkairec/request/v20181012/DeleteDiversifyRequest.py
aliyunsdkairec/request/v20181012/DeleteMixRequest.py
aliyunsdkairec/request/v20181012/DescribeDashboardRequest.py
aliyunsdkairec/request/v20181012/DescribeDataSetMessageRequest.py
aliyunsdkairec/request/v20181012/DescribeDataSetReportRequest.py
aliyunsdkairec/request/v20181012/DescribeDiversifyRequest.py
aliyunsdkairec/request/v20181012/DescribeExposureSettingsRequest.py
aliyunsdkairec/request/v20181012/DescribeInstanceRequest.py
aliyunsdkairec/request/v20181012/DescribeMixRequest.py
aliyunsdkairec/request/v20181012/DescribeQuotaRequest.py
aliyunsdkairec/request/v20181012/DescribeSchemaRequest.py
aliyunsdkairec/request/v20181012/ListDashboardParametersRequest.py
aliyunsdkairec/request/v20181012/ListDashboardRequest.py
aliyunsdkairec/request/v20181012/ListDashboardUidRequest.py
aliyunsdkairec/request/v20181012/ListDataSetRequest.py
aliyunsdkairec/request/v20181012/ListDataSourceRequest.py
aliyunsdkairec/request/v20181012/ListDiversifyRequest.py
aliyunsdkairec/request/v20181012/ListInstanceRequest.py
aliyunsdkairec/request/v20181012/ListInstanceTaskRequest.py
aliyunsdkairec/request/v20181012/ListMixRequest.py
aliyunsdkairec/request/v20181012/ModifyDataSourceRequest.py
aliyunsdkairec/request/v20181012/ModifyDiversifyRequest.py
aliyunsdkairec/request/v20181012/ModifyExposureSettingsRequest.py
aliyunsdkairec/request/v20181012/ModifyInstanceRequest.py
aliyunsdkairec/request/v20181012/ModifyMixRequest.py
aliyunsdkairec/request/v20181012/PushDocumentRequest.py
aliyunsdkairec/request/v20181012/PushInterventionRequest.py
